puppy/__init__.py
puppy/puppy.py
puppy/core/HTMLTestRunner.py
puppy/core/__init__.py
puppy/core/ddt.py
puppy/core/api/__init__.py
puppy/core/api/common/__init__.py
puppy/core/api/common/res_data.py
puppy/core/api/process/__init__.py
puppy/core/api/process/post.py
puppy/core/api/process/pre.py
puppy/core/api/processor/__init__.py
puppy/core/api/processor/processor.py
puppy/core/api/processor/client/__init__.py
puppy/core/api/processor/client/client.py
puppy/core/api/processor/client/http.py
puppy/core/api/processor/client/sql.py
puppy/core/api/processor/client/tcp.py
puppy/core/data/__init__.py
puppy/core/data/flow.py
puppy/core/data/interface.py
puppy/core/data/test_data.py
puppy/core/exception/__init__.py
puppy/core/exception/client.py
puppy/core/exception/db.py
puppy/core/exception/expect.py
puppy/core/exception/inf_process.py
puppy/core/exception/my_assertion_error.py
puppy/core/exception/my_exception.py
puppy/core/exception/other.py
puppy/core/exception/post.py
puppy/core/exception/pre.py
puppy/core/function/__init__.py
puppy/core/function/analysis/__init__.py
puppy/core/function/analysis/xml_parser.py
puppy/core/function/beautify/__init__.py
puppy/core/function/beautify/beautify.py
puppy/core/function/beautify/beautify_json.py
puppy/core/function/beautify/beautify_xml.py
puppy/core/function/beautify/fold.py
puppy/core/function/cfg/__init__.py
puppy/core/function/cfg/config.py
puppy/core/function/cfg/my_configparser.py
puppy/core/function/cookies/__init__.py
puppy/core/function/cookies/cookie.py
puppy/core/function/database/__init__.py
puppy/core/function/database/db.py
puppy/core/function/env/__init__.py
puppy/core/function/env/environment.py
puppy/core/function/express/__init__.py
puppy/core/function/express/express.py
puppy/core/function/express/function.py
puppy/core/function/func/__init__.py
puppy/core/function/func/module.py
puppy/core/function/jvm/__init__.py
puppy/core/function/jvm/jvm.py
puppy/core/function/jvm/jvm_process.py
puppy_test-1.3.1.dist-info/LICENSE
puppy_test-1.3.1.dist-info/METADATA
puppy_test-1.3.1.dist-info/WHEEL
puppy_test-1.3.1.dist-info/entry_points.txt
puppy_test-1.3.1.dist-info/top_level.txt
puppy_test-1.3.1.dist-info/RECORD
