Metadata-Version: 2.1
Name: puppy-test
Version: 1.3.1
Summary: UNKNOWN
Home-page: UNKNOWN
Author: Li Junxian
Author-email: yk690520@outlook.com
License: UNKNOWN
Platform: UNKNOWN
License-File: LICENSE
Requires-Dist: requests (>=2.25.0)
